{
    "bug-reports": {
        "title": "Bug Reports",
        "slug": "bug-reports",
        "markdown_source": "https:\/\/github.com\/wp-cli\/handbook\/blob\/main\/bug-reports.md",
        "parent": null
    },
    "code-review": {
        "title": "Code Review",
        "slug": "code-review",
        "markdown_source": "https:\/\/github.com\/wp-cli\/handbook\/blob\/main\/code-review.md",
        "parent": null
    },
    "commands-cookbook": {
        "title": "Commands Cookbook",
        "slug": "commands-cookbook",
        "markdown_source": "https:\/\/github.com\/wp-cli\/handbook\/blob\/main\/commands-cookbook.md",
        "parent": null
    },
    "committers-credo": {
        "title": "Committers Credo",
        "slug": "committers-credo",
        "markdown_source": "https:\/\/github.com\/wp-cli\/handbook\/blob\/main\/committers-credo.md",
        "parent": null
    },
    "common-issues": {
        "title": "Common Issues",
        "slug": "common-issues",
        "markdown_source": "https:\/\/github.com\/wp-cli\/handbook\/blob\/main\/common-issues.md",
        "parent": null
    },
    "config": {
        "title": "Config",
        "slug": "config",
        "markdown_source": "https:\/\/github.com\/wp-cli\/handbook\/blob\/main\/config.md",
        "parent": null
    },
    "contributing": {
        "title": "Contributing",
        "slug": "contributing",
        "markdown_source": "https:\/\/github.com\/wp-cli\/handbook\/blob\/main\/contributing.md",
        "parent": null
    },
    "contributor-day": {
        "title": "WordCamp Contributor Day",
        "slug": "contributor-day",
        "markdown_source": "https:\/\/github.com\/wp-cli\/handbook\/blob\/main\/contributor-day.md",
        "parent": null
    },
    "doctor-check-constant-value": {
        "title": "Write a check for asserting the value of a given constant",
        "slug": "doctor-check-constant-value",
        "markdown_source": "https:\/\/github.com\/wp-cli\/handbook\/blob\/main\/doctor-check-constant-value.md",
        "parent": null
    },
    "doctor-check-file-contents": {
        "title": "Write a check for verifying contents of WordPress files",
        "slug": "doctor-check-file-contents",
        "markdown_source": "https:\/\/github.com\/wp-cli\/handbook\/blob\/main\/doctor-check-file-contents.md",
        "parent": null
    },
    "doctor-check-option-value": {
        "title": "Write a check for asserting the value of a given option",
        "slug": "doctor-check-option-value",
        "markdown_source": "https:\/\/github.com\/wp-cli\/handbook\/blob\/main\/doctor-check-option-value.md",
        "parent": null
    },
    "doctor-check-plugin-status": {
        "title": "Check status of a given plugin",
        "slug": "doctor-check-plugin-status",
        "markdown_source": "https:\/\/github.com\/wp-cli\/handbook\/blob\/main\/doctor-check-plugin-status.md",
        "parent": null
    },
    "doctor-customize-config": {
        "title": "Customize doctor diagnostic checks",
        "slug": "doctor-customize-config",
        "markdown_source": "https:\/\/github.com\/wp-cli\/handbook\/blob\/main\/doctor-customize-config.md",
        "parent": null
    },
    "doctor-default-checks": {
        "title": "Default doctor diagnostic checks",
        "slug": "doctor-default-checks",
        "markdown_source": "https:\/\/github.com\/wp-cli\/handbook\/blob\/main\/doctor-default-checks.md",
        "parent": null
    },
    "doctor-write-custom-check": {
        "title": "Write a custom check to perform an arbitrary assertion",
        "slug": "doctor-write-custom-check",
        "markdown_source": "https:\/\/github.com\/wp-cli\/handbook\/blob\/main\/doctor-write-custom-check.md",
        "parent": null
    },
    "doctor": {
        "title": "Doctor Guides",
        "slug": "doctor",
        "markdown_source": "https:\/\/github.com\/wp-cli\/handbook\/blob\/main\/doctor.md",
        "parent": null
    },
    "documentation-standards": {
        "title": "Documentation Standards",
        "slug": "documentation-standards",
        "markdown_source": "https:\/\/github.com\/wp-cli\/handbook\/blob\/main\/documentation-standards.md",
        "parent": null
    },
    "external-resources": {
        "title": "External Resources",
        "slug": "external-resources",
        "markdown_source": "https:\/\/github.com\/wp-cli\/handbook\/blob\/main\/external-resources.md",
        "parent": null
    },
    "force-output-specific-locale": {
        "title": "Force output to a specific locale",
        "slug": "force-output-specific-locale",
        "markdown_source": "https:\/\/github.com\/wp-cli\/handbook\/blob\/main\/force-output-specific-locale.md",
        "parent": null
    },
    "governance": {
        "title": "Governance",
        "slug": "governance",
        "markdown_source": "https:\/\/github.com\/wp-cli\/handbook\/blob\/main\/governance.md",
        "parent": null
    },
    "hack-day": {
        "title": "WP-CLI Hack Day",
        "slug": "hack-day",
        "markdown_source": "https:\/\/github.com\/wp-cli\/handbook\/blob\/main\/hack-day.md",
        "parent": null
    },
    "hosting-companies": {
        "title": "Hosting Companies",
        "slug": "hosting-companies",
        "markdown_source": "https:\/\/github.com\/wp-cli\/handbook\/blob\/main\/hosting-companies.md",
        "parent": null
    },
    "how-to-create-custom-plugins": {
        "title": "",
        "slug": "how-to-create-custom-plugins",
        "markdown_source": "https:\/\/github.com\/wp-cli\/handbook\/blob\/main\/how-to-create-custom-plugins.md",
        "parent": null
    },
    "how-to-install": {
        "title": "How to install WordPress",
        "slug": "how-to-install",
        "markdown_source": "https:\/\/github.com\/wp-cli\/handbook\/blob\/main\/how-to-install.md",
        "parent": null
    },
    "how-to-maintenance-mode": {
        "title": "How to put the site in maintenance mode",
        "slug": "how-to-maintenance-mode",
        "markdown_source": "https:\/\/github.com\/wp-cli\/handbook\/blob\/main\/how-to-maintenance-mode.md",
        "parent": null
    },
    "how-to-start-webserver": {
        "title": "How to start the webserver",
        "slug": "how-to-start-webserver",
        "markdown_source": "https:\/\/github.com\/wp-cli\/handbook\/blob\/main\/how-to-start-webserver.md",
        "parent": null
    },
    "how-to": {
        "title": "How to WP-CLI",
        "slug": "how-to",
        "markdown_source": "https:\/\/github.com\/wp-cli\/handbook\/blob\/main\/how-to.md",
        "parent": null
    },
    "identify-plugin-theme-conflict": {
        "title": "Identify a Plugin or Theme Conflict",
        "slug": "identify-plugin-theme-conflict",
        "markdown_source": "https:\/\/github.com\/wp-cli\/handbook\/blob\/main\/identify-plugin-theme-conflict.md",
        "parent": null
    },
    "implementation-details": {
        "title": "Implementation Details",
        "slug": "implementation-details",
        "markdown_source": "https:\/\/github.com\/wp-cli\/handbook\/blob\/main\/implementation-details.md",
        "parent": null
    },
    "index": {
        "title": "Handbook",
        "slug": "handbook",
        "markdown_source": "https:\/\/github.com\/wp-cli\/handbook\/blob\/main\/index.md",
        "parent": null
    },
    "installing": {
        "title": "Installing",
        "slug": "installing",
        "markdown_source": "https:\/\/github.com\/wp-cli\/handbook\/blob\/main\/installing.md",
        "parent": null
    },
    "internal-api": {
        "title": "Internal API",
        "slug": "internal-api",
        "markdown_source": "https:\/\/github.com\/wp-cli\/handbook\/blob\/main\/internal-api.md",
        "parent": null
    },
    "philosophy": {
        "title": "Philosophy",
        "slug": "philosophy",
        "markdown_source": "https:\/\/github.com\/wp-cli\/handbook\/blob\/main\/philosophy.md",
        "parent": null
    },
    "plugin-unit-tests": {
        "title": "Plugin Integration Tests",
        "slug": "plugin-unit-tests",
        "markdown_source": "https:\/\/github.com\/wp-cli\/handbook\/blob\/main\/plugin-unit-tests.md",
        "parent": null
    },
    "pull-requests": {
        "title": "Pull Requests",
        "slug": "pull-requests",
        "markdown_source": "https:\/\/github.com\/wp-cli\/handbook\/blob\/main\/pull-requests.md",
        "parent": null
    },
    "quick-start": {
        "title": "Quick Start",
        "slug": "quick-start",
        "markdown_source": "https:\/\/github.com\/wp-cli\/handbook\/blob\/main\/quick-start.md",
        "parent": null
    },
    "release-checklist": {
        "title": "Release Checklist",
        "slug": "release-checklist",
        "markdown_source": "https:\/\/github.com\/wp-cli\/handbook\/blob\/main\/release-checklist.md",
        "parent": null
    },
    "repository-management": {
        "title": "Repository Management",
        "slug": "repository-management",
        "markdown_source": "https:\/\/github.com\/wp-cli\/handbook\/blob\/main\/repository-management.md",
        "parent": null
    },
    "roadmap": {
        "title": "Roadmap",
        "slug": "roadmap",
        "markdown_source": "https:\/\/github.com\/wp-cli\/handbook\/blob\/main\/roadmap.md",
        "parent": null
    },
    "running-commands-remotely": {
        "title": "Running Commands Remotely",
        "slug": "running-commands-remotely",
        "markdown_source": "https:\/\/github.com\/wp-cli\/handbook\/blob\/main\/running-commands-remotely.md",
        "parent": null
    },
    "sharing-wp-cli-packages": {
        "title": "Sharing WP-CLI Packages",
        "slug": "sharing-wp-cli-packages",
        "markdown_source": "https:\/\/github.com\/wp-cli\/handbook\/blob\/main\/sharing-wp-cli-packages.md",
        "parent": null
    },
    "shell-friends": {
        "title": "Shell Friends",
        "slug": "shell-friends",
        "markdown_source": "https:\/\/github.com\/wp-cli\/handbook\/blob\/main\/shell-friends.md",
        "parent": null
    },
    "tools": {
        "title": "Tools",
        "slug": "tools",
        "markdown_source": "https:\/\/github.com\/wp-cli\/handbook\/blob\/main\/tools.md",
        "parent": null
    },
    "troubleshooting": {
        "title": "Troubleshooting Guide",
        "slug": "troubleshooting",
        "markdown_source": "https:\/\/github.com\/wp-cli\/handbook\/blob\/main\/troubleshooting.md",
        "parent": null
    }
}